LICENSE
MANIFEST.in
README.rst
setup.py
jook/__init__.py
jook/exceptions.py
jook/identifiers.py
jook.egg-info/PKG-INFO
jook.egg-info/SOURCES.txt
jook.egg-info/dependency_links.txt
jook.egg-info/not-zip-safe
jook.egg-info/requires.txt
jook.egg-info/top_level.txt
jook/models/__init__.py
jook/models/data_sets.py
jook/models/webhooks.py