Metadata-Version: 1.1
Name: jook
Version: 0.4.3
Summary: A Jamf Pro webhook simulator
Home-page: https://github.com/brysontyrrell/Jook
Author: Bryson Tyrrell
Author-email: bryson.tyrrell@gmail.com
License: MIT
Keywords: jamf webhooks testing development tools
Platform: UNKNOWN
Classifier: Development Status :: 3 - Alpha
Classifier: Intended Audience :: Developers
Classifier: Intended Audience :: Information Technology
Classifier: License :: OSI Approved :: MIT License
Classifier: Programming Language :: Python :: 2.7
